machine_dialect/__main__.py
machine_dialect/agent/__init__.py
machine_dialect/agent/agent.py
machine_dialect/ast/__init__.py
machine_dialect/ast/ast_node.py
machine_dialect/ast/call_expression.py
machine_dialect/ast/dict_extraction.py
machine_dialect/ast/expressions.py
machine_dialect/ast/literals.py
machine_dialect/ast/program.py
machine_dialect/ast/statements.py
machine_dialect/ast/tests/test_ast_string_representation.py
machine_dialect/ast/tests/test_boolean_literal.py
machine_dialect/ast/tests/test_collection_hir.py
machine_dialect/ast/tests/test_define_statement.py
machine_dialect/ast/tests/test_desugar.py
machine_dialect/ast/tests/test_foreach_desugar.py
machine_dialect/cfg/__init__.py
machine_dialect/cfg/config.py
machine_dialect/cfg/examples.py
machine_dialect/cfg/generate_with_ai.py
machine_dialect/cfg/openai_generation.py
machine_dialect/cfg/parser.py
machine_dialect/cfg/tests/__init__.py
machine_dialect/cfg/tests/test_cfg_parser.py
machine_dialect/cfg/tests/test_config.py
machine_dialect/cfg/tests/test_examples.py
machine_dialect/cfg/tests/test_generate_with_ai.py
machine_dialect/cfg/tests/test_openai_generation.py
machine_dialect/codegen/__init__.py
machine_dialect/codegen/bytecode_module.py
machine_dialect/codegen/bytecode_serializer.py
machine_dialect/codegen/opcodes.py
machine_dialect/codegen/register_codegen.py
machine_dialect/codegen/symtab.py
machine_dialect/codegen/vm_serializer.py
machine_dialect/codegen/tests/__init__.py
machine_dialect/codegen/tests/test_array_operations_codegen.py
machine_dialect/codegen/tests/test_bytecode_serializer.py
machine_dialect/codegen/tests/test_register_codegen_ssa.py
machine_dialect/codegen/tests/test_symtab.py
machine_dialect/compiler/__init__.py
machine_dialect/compiler/compiler.py
machine_dialect/compiler/config.py
machine_dialect/compiler/context.py
machine_dialect/compiler/pipeline.py
machine_dialect/compiler/vm_runner.py
machine_dialect/compiler/phases/__init__.py
machine_dialect-0.1.0a2.dist-info/licenses/LICENSE
machine_dialect-0.1.0a2.dist-info/METADATA
machine_dialect-0.1.0a2.dist-info/WHEEL
machine_dialect-0.1.0a2.dist-info/entry_points.txt
machine_dialect-0.1.0a2.dist-info/top_level.txt
machine_dialect-0.1.0a2.dist-info/RECORD
