Metadata-Version: 2.4
Name: machine-dialect
Version: 0.1.0a2
Summary: Machine Dialect™ - Natural language programming in Markdown
Author: Lajara AI, LLC
Project-URL: Homepage, https://github.com/kennylajara/machine-dialect
Project-URL: Bug Tracker, https://github.com/kennylajara/machine-dialect/issues
Keywords: programming-language,natural-language,markdown,compiler
Classifier: Development Status :: 3 - Alpha
Classifier: Intended Audience :: Developers
Classifier: License :: OSI Approved :: Apache Software License
Classifier: Programming Language :: Python :: 3
Classifier: Programming Language :: Python :: 3.10
Classifier: Programming Language :: Python :: 3.11
Classifier: Programming Language :: Python :: 3.12
Classifier: Programming Language :: Python :: 3.13
Classifier: Topic :: Software Development :: Code Generators
Classifier: Topic :: Software Development :: Compilers
Classifier: Topic :: Software Development :: Interpreters
Requires-Python: <=13,>=3.10
License-File: LICENSE
Requires-Dist: rfc3986==2.0.0
Requires-Dist: click==8.2.1
Requires-Dist: lark==1.2.2
Requires-Dist: openai==1.99.9
Requires-Dist: machine-dialect-vm==0.1.0a2
Dynamic: license-file
